perforce/__init__.py
perforce/api.py
perforce/errors.py
perforce/models.py
python_perforce-0.5.2.dist-info/LICENSE
python_perforce-0.5.2.dist-info/METADATA
python_perforce-0.5.2.dist-info/WHEEL
python_perforce-0.5.2.dist-info/top_level.txt
python_perforce-0.5.2.dist-info/RECORD
