Metadata-Version: 2.1
Name: python-perforce
Version: 0.5.2
Summary: Pure python Perforce API
Home-page: https://github.com/theiviaxx/python-perforce
Author: Brett Dixon
Author-email: theiviaxx@gmail.com
License: MIT
Keywords: python-perforce
Platform: UNKNOWN
Classifier: Development Status :: 2 - Pre-Alpha
Classifier: Intended Audience :: Developers
Classifier: License :: OSI Approved :: MIT License
Classifier: Natural Language :: English
Classifier: Programming Language :: Python :: 2.7
Classifier: Programming Language :: Python :: 3.5
Requires-Dist: path.py (==8.1.1)
Requires-Dist: six (==1.10.0)
